{
  "stock_id": "4589",
  "stock_name": "碩陽電機",
  "industry_category": "電機機械",
  "type": "emerging",
  "backtest_period": "2024-02-15 ~ 2026-02-25",
  "initial_capital": 1000000,
  "buy_and_hold_return_pct": 27.4,
  "daily_volatility_pct": 2.54,
  "viable_strategies": [
    {
      "rank": 1,
      "name": "威廉%R(14)",
      "category": "逆勢",
      "description": "Williams %R<-80買入，>-20賣出",
      "stop_loss": "ATR停損：買入價-2×ATR(14)",
      "total_return_pct": 67.2,
      "final_capital": 1672047,
      "trades": 16,
      "win_rate_pct": 81.2,
      "avg_holding_days": 25.1,
      "max_drawdown_pct": 13.95,
      "sharpe_ratio": 1.04,
      "stop_loss_count": 3
    }
  ],
  "backtest_engine": "backtest.py",
  "engine_version": "v2"
}