{
  "stock_id": "5244",
  "stock_name": "弘凱",
  "industry_category": "電子工業",
  "type": "twse",
  "backtest_period": "2024-02-15 ~ 2026-02-25",
  "initial_capital": 1000000,
  "buy_and_hold_return_pct": 23.6,
  "daily_volatility_pct": 2.83,
  "viable_strategies": [
    {
      "rank": 1,
      "name": "RSI+Bollinger",
      "category": "逆勢",
      "description": "RSI(14)<35且低於布林下軌買入，RSI>65或碰上軌賣出",
      "stop_loss": "ATR停損：買入價-2.5×ATR(14)",
      "total_return_pct": 72.46,
      "final_capital": 1724589,
      "trades": 5,
      "win_rate_pct": 80.0,
      "avg_holding_days": 51.0,
      "max_drawdown_pct": 16.22,
      "sharpe_ratio": 1.12,
      "stop_loss_count": 1
    },
    {
      "rank": 2,
      "name": "RSI背離反彈",
      "category": "逆勢",
      "description": "價格創新低但RSI(14)未創新低（背離）買入，RSI>55賣出",
      "stop_loss": "ATR停損：買入價-2×ATR(14)",
      "total_return_pct": 51.41,
      "final_capital": 1514066,
      "trades": 11,
      "win_rate_pct": 63.6,
      "avg_holding_days": 23.0,
      "max_drawdown_pct": 14.61,
      "sharpe_ratio": 1.04,
      "stop_loss_count": 3
    }
  ],
  "backtest_engine": "backtest.py",
  "engine_version": "v2"
}